nislsypy/__init__.py
nislsypy/setup.py
nislsypy/flydisp/__init__.py
nislsypy/flydisp/edrfunc.py
nislsypy/flydisp/utils.py
nislsypy/flydisppat/__init__.py
nislsypy/flydisppat/genfunc.py
nislsypy/flydisppat/utils.py
nislsypy/flydisppat/visfunc.py
nislsypy-0.0.4.dist-info/METADATA
nislsypy-0.0.4.dist-info/WHEEL
nislsypy-0.0.4.dist-info/top_level.txt
nislsypy-0.0.4.dist-info/RECORD
